server_logger/__init__.py
server_logger/utils.py
django_server_logger-1.0.1.dist-info/METADATA
django_server_logger-1.0.1.dist-info/WHEEL
django_server_logger-1.0.1.dist-info/entry_points.txt
django_server_logger-1.0.1.dist-info/top_level.txt
django_server_logger-1.0.1.dist-info/RECORD
